[
  {
    "id": "1",
    "isStarted": false,
    "isEnded": false,
    "isFinished": false,
    "demandDict": [
      [
        "numdemand",
        "1"
      ]
    ],
    "type": "主线任务",
    "level": 1
  },
  {
    "id": "2",
    "isStarted": false,
    "isEnded": false,
    "isFinished": false,
    "demandDict": [
      [
        "numdemand",
        "2"
      ]
    ],
    "type": "主线任务",
    "level": 1
  },
  {
    "id": "3",
    "isStarted": false,
    "isEnded": false,
    "isFinished": false,
    "demandDict": [
      [
        "numdemand",
        "3"
      ]
    ],
    "type": "主线任务",
    "level": 1
  },
  {
    "id": "4",
    "isStarted": false,
    "isEnded": false,
    "isFinished": false,
    "demandDict": [
      [
        "numdemand",
        "4"
      ]
    ],
    "type": "主线任务",
    "level": 1
  },
  {
    "id": "5",
    "isStarted": false,
    "isEnded": false,
    "isFinished": false,
    "demandDict": [
      [
        "numdemand",
        "5"
      ]
    ],
    "type": "主线任务",
    "level": 1
  },
  {
    "id": "6",
    "isStarted": false,
    "isEnded": false,
    "isFinished": false,
    "demandDict": [
      [
        "numdemand",
        "6"
      ]
    ],
    "type": "主线任务",
    "level": 1
  },
  {
    "id": "7",
    "isStarted": false,
    "isEnded": false,
    "isFinished": false,
    "demandDict": [
      [
        "numdemand",
        "7"
      ]
    ],
    "type": "主线任务",
    "level": 2
  },
  {
    "id": "8",
    "isStarted": false,
    "isEnded": false,
    "isFinished": false,
    "demandDict": [
      [
        "numdemand",
        "8"
      ]
    ],
    "type": "主线任务",
    "level": 2
  },
  {
    "id": "9",
    "isStarted": false,
    "isEnded": false,
    "isFinished": false,
    "demandDict": [
      [
        "numdemand",
        "9"
      ]
    ],
    "type": "主线任务",
    "level": 2
  },
  {
    "id": "10",
    "isStarted": false,
    "isEnded": false,
    "isFinished": false,
    "demandDict": [
      [
        "numdemand",
        "10"
      ]
    ],
    "type": "主线任务",
    "level": 2
  },
  {
    "id": "11",
    "isStarted": false,
    "isEnded": false,
    "isFinished": false,
    "demandDict": [
      [
        "numdemand",
        "11"
      ]
    ],
    "type": "主线任务",
    "level": 3
  },
  {
    "id": "12",
    "isStarted": false,
    "isEnded": false,
    "isFinished": false,
    "demandDict": [
      [
        "numdemand",
        "12"
      ]
    ],
    "type": "主线任务",
    "level": 3
  },
  {
    "id": "13",
    "isStarted": false,
    "isEnded": false,
    "isFinished": false,
    "demandDict": [
      [
        "numdemand",
        "15"
      ]
    ],
    "type": "主线任务",
    "level": 3
  },
  {
    "id": "14",
    "isStarted": false,
    "isEnded": false,
    "isFinished": false,
    "demandDict": [
      [
        "numdemand",
        "13"
      ]
    ],
    "type": "主线任务",
    "level": 1
  },
  {
    "id": "15",
    "isStarted": false,
    "isEnded": false,
    "isFinished": false,
    "demandDict": [
      [
        "numdemand",
        "14"
      ]
    ],
    "type": "主线任务",
    "level": 2
  },
  {
    "id": "16",
    "isStarted": false,
    "isEnded": false,
    "isFinished": false,
    "demandDict": [
      [
        "numdemand",
        "16"
      ]
    ],
    "type": "支线任务",
    "level": 0
  }
]